setup.py
esms/__init__.py
esms/client.py
esms/endpoints.py
esms.egg-info/PKG-INFO
esms.egg-info/SOURCES.txt
esms.egg-info/dependency_links.txt
esms.egg-info/top_level.txt