Metadata-Version: 2.1
Name: esms
Version: 0.0.1
Summary: Send SMS via carrier specific email gateways
Home-page: https://github.com/3jackdaws/esms
Author: Ian Murphy
Author-email: 3jackdaws@gmail.com
License: MIT
Platform: UNKNOWN
Requires-Python: >=3.5
